benchmarkstt/__init__.py
benchmarkstt/__meta__.py
benchmarkstt/config.py
benchmarkstt/csv.py
benchmarkstt/decorators.py
benchmarkstt/deferred.py
benchmarkstt/docblock.py
benchmarkstt/factory.py
benchmarkstt/helpers.py
benchmarkstt/modules.py
benchmarkstt/registry.py
benchmarkstt/schema.py
benchmarkstt/api/__init__.py
benchmarkstt/api/gunicorn.py
benchmarkstt/api/jsonrpc.py
benchmarkstt/api/entrypoints/__init__.py
benchmarkstt/api/entrypoints/api.py
benchmarkstt/api/entrypoints/benchmark.py
benchmarkstt/api/entrypoints/metrics.py
benchmarkstt/api/entrypoints/normalization.py
benchmarkstt/api/templates/api-explorer.html
benchmarkstt/cli/__init__.py
benchmarkstt/cli/main.py
benchmarkstt/cli/tools.py
benchmarkstt/cli/entrypoints/__init__.py
benchmarkstt/cli/entrypoints/api.py
benchmarkstt/cli/entrypoints/benchmark.py
benchmarkstt/cli/entrypoints/metrics.py
benchmarkstt/cli/entrypoints/normalization.py
benchmarkstt/diff/__init__.py
benchmarkstt/diff/core.py
benchmarkstt/diff/formatter.py
benchmarkstt/input/__init__.py
benchmarkstt/input/core.py
benchmarkstt/metrics/__init__.py
benchmarkstt/metrics/core.py
benchmarkstt/normalization/__init__.py
benchmarkstt/normalization/core.py
benchmarkstt/normalization/logger.py
benchmarkstt/output/__init__.py
benchmarkstt/output/core.py
benchmarkstt/segmentation/__init__.py
benchmarkstt/segmentation/core.py
benchmarkstt-1.1.dist-info/LICENCE.md
benchmarkstt-1.1.dist-info/METADATA
benchmarkstt-1.1.dist-info/WHEEL
benchmarkstt-1.1.dist-info/entry_points.txt
benchmarkstt-1.1.dist-info/top_level.txt
benchmarkstt-1.1.dist-info/RECORD
