Metadata-Version: 2.1
Name: benchmarkstt
Version: 1.1
Summary: A library for benchmarking AI/ML applications.
Home-page: https://github.com/ebu/benchmarkstt/
Author: EBU
Author-email: ai-stt@list.ebu.ch
Maintainer: EBU
Maintainer-email: ai-stt@list.ebu.ch
License: MIT
Platform: any
Classifier: Programming Language :: Python
Classifier: Programming Language :: Python :: 3
Classifier: Programming Language :: Python :: 3.5
Classifier: Programming Language :: Python :: 3.6
Classifier: Programming Language :: Python :: 3.7
Classifier: Programming Language :: Python :: 3.8
Classifier: Programming Language :: Python :: 3.9
Classifier: License :: OSI Approved :: MIT License
Requires-Python: >=3.5
Requires-Dist: MarkupSafe (>=1.0)
Requires-Dist: Flask (>=1.0.2)
Requires-Dist: jsonrpcserver (>=4.0.1)
Requires-Dist: gunicorn (>=19.9.0)
Requires-Dist: docutils (>=0.14)
Requires-Dist: editdistance (>=0.5.3)
Requires-Dist: Unidecode (>=1.1.2)
Provides-Extra: docs
Requires-Dist: sphinx (==3.2.1) ; extra == 'docs'
Requires-Dist: sphinx-rtd-theme (==0.4.2) ; extra == 'docs'
Requires-Dist: sphinx-argparse (==0.2.5) ; extra == 'docs'
Requires-Dist: sphinxcontrib-mermaid (==0.4.0) ; extra == 'docs'
Provides-Extra: test
Requires-Dist: pytest (==4.2.0) ; extra == 'test'
Requires-Dist: pycodestyle (==2.5.0) ; extra == 'test'
Requires-Dist: pytest-cov (==2.5.1) ; extra == 'test'
Requires-Dist: attrs (==19.1.0) ; extra == 'test'
